intelliw_onnx/__init__.py
intelliw_onnx/main.py
intelliw_onnx/common/__init__.py
intelliw_onnx/common/correct_batch.py
intelliw_onnx/common/mish_convert.py
intelliw_onnx/common/operation.py
intelliw_onnx/common/swish_convert.py
intelliw_onnx/common/to_float16.py
intelliw_onnx/common/to_uint8.py
intelliw_onnx/common/values.py
intelliw_onnx/common/version_check.py
intelliw_onnx/convert/__init__.py
intelliw_onnx/convert/convert.py
intelliw_onnx/convert/exit_code.py
intelliw_onnx/convert/make_args.py
intelliw_onnx/convert/pd2onnx.py
intelliw_onnx/convert/pt2onnx.py
intelliw_onnx/convert/utils.py
intelliw_onnx/logs/intelliw-onnx.log
intelliw_onnx/logs/iw-algo-fx.log
intelliw_onnx/logs/iw-algo-fx.log.2023-11-09.log
intelliw_onnx/static/intelliw_infer.py
intelliw_onnx/test/__init__.py
intelliw_onnx/test/params.py
intelliw_onnx/test/test_onnx_demo.py
intelliw_onnx/test/test_pd2onnx.py
intelliw_onnx/test/test_pt2onnx.py
intelliw_onnx/test/logs/intelliw-onnx.log
intelliw_onnx/test/logs/iw-algo-fx.log
intelliw_onnx/utils/__init__.py
intelliw_onnx/utils/exception.py
intelliw_onnx/utils/global_val.py
intelliw_onnx/utils/logger.py
intelliw_onnx-0.0.4.dist-info/LICENCE
intelliw_onnx-0.0.4.dist-info/METADATA
intelliw_onnx-0.0.4.dist-info/WHEEL
intelliw_onnx-0.0.4.dist-info/entry_points.txt
intelliw_onnx-0.0.4.dist-info/top_level.txt
intelliw_onnx-0.0.4.dist-info/RECORD
