Metadata-Version: 2.1
Name: intelliw-onnx
Version: 0.0.4
Summary: An easy to start Intelligent Workshop Algorithm Framework
Home-page: http://git.yonyou.com/iuapaipaas/intelliw-onnx
Author: yonyou
Author-email: yonyou@yonyou.com
Classifier: Development Status :: 3 - Alpha
Classifier: Programming Language :: Python :: 3.8
Classifier: Programming Language :: Python :: 3.9
Classifier: Programming Language :: Python :: 3.10
Classifier: Programming Language :: Python :: 3.11
Classifier: Operating System :: OS Independent
Requires-Python: >=3.8
License-File: LICENCE
Requires-Dist: numpy >=1.20
Requires-Dist: onnx >=1.14
Requires-Dist: onnxsim >=0.4.33
Requires-Dist: onnxruntime >=1.15
